{
  "$schema": "https://mintlify.com/docs.json",
  "theme": "willow",
  "name": "Bluebox Scripts",
  "colors": {
    "primary": "#007CE7",
    "light": "#3399FF",
    "dark": "#0066CC"
  },
  "favicon": "/favicon.svg",
  "navigation": {
    "tabs": [
      {
        "tab": "Bluebox Scripts",
        "groups": [
          {
            "group": "Welcome",
            "pages": [
              "index"
            ]
          },
          {
            "group": "Scripts",
            "pages": ["scripts/npc-removal"]
          }
        ]
      }
    ],
    "global": {
      "anchors": [
        {
          "anchor": "Discord",
          "href": "https://discord.gg/K5KpCKs8Zf",
          "icon": "discord"
        },
        {
          "anchor": "YouTube",
          "href": "https://www.youtube.com/@blueboxscripts",
          "icon": "youtube"
        },
        {
          "anchor": "Buy our scripts",
          "href": "https://blueboxscripts.com",
          "icon": "store"
        }
      ]
    }
  },
  "logo": {
    "light": "/logo/light.svg",
    "dark": "/logo/dark.svg"
  },
  "navbar": {
    "links": [
      {
        "label": "Support",
        "href": "https://discord.gg/blueboxscripts"
      }
    ],
    "primary": {
      "type": "button",
      "label": "Dashboard",
      "href": "https://docs.blueboxscripts.com"
    }
  },
  "footer": {
    "socials": {
      "x": "https://x.com/blueboxscripts",
      "instagram": "https://www.instagram.com/blueboxscripts/"
    }
  }
}